<scene name='ARQ-57'>
    <object name='TLAMP' x='-7.0000' y='3.7000' z='0.0000' rx='0.0000' ry='0.0000' rz='0.0000' sx='1.0' sy='1.0' sz='1.0'></object>
    <object name='TLAMP' x='-7.0000' y='2.2000' z='0.0000' rx='0.0000' ry='0.0000' rz='0.0000' sx='1.0' sy='1.0' sz='1.0'></object>
    <object name='TLAMP' x='-7.0000' y='0.7000' z='0.0000' rx='0.0000' ry='0.0000' rz='0.0000' sx='1.0' sy='1.0' sz='1.0'></object>
    <object name='TLAMP' x='-5.0000' y='3.7000' z='0.0000' rx='0.0000' ry='0.0000' rz='0.0000' sx='1.0' sy='1.0' sz='1.0'></object>
    <object name='TLAMP' x='-5.0000' y='2.2000' z='0.0000' rx='0.0000' ry='0.0000' rz='0.0000' sx='1.0' sy='1.0' sz='1.0'></object>
    <object name='TLAMP' x='-5.0000' y='0.7000' z='0.0000' rx='0.0000' ry='0.0000' rz='0.0000' sx='1.0' sy='1.0' sz='1.0'></object>
    <object name='TLAMP' x='-1.8622' y='3.7000' z='0.0000' rx='0.0000' ry='0.0000' rz='0.0000' sx='1.0' sy='1.0' sz='1.0'></object>
    <object name='TLAMP' x='-1.8622' y='2.2000' z='0.0000' rx='0.0000' ry='0.0000' rz='0.0000' sx='1.0' sy='1.0' sz='1.0'></object>
    <object name='TLAMP' x='-1.8622' y='0.7000' z='0.0000' rx='0.0000' ry='0.0000' rz='0.0000' sx='1.0' sy='1.0' sz='1.0'></object>
    <object name='TLAMP' x='0.1378' y='3.7000' z='0.0000' rx='0.0000' ry='0.0000' rz='0.0000' sx='1.0' sy='1.0' sz='1.0'></object>
    <object name='TLAMP' x='0.1378' y='2.2000' z='0.0000' rx='0.0000' ry='0.0000' rz='0.0000' sx='1.0' sy='1.0' sz='1.0'></object>
    <object name='TLAMP' x='0.1378' y='0.7000' z='0.0000' rx='0.0000' ry='0.0000' rz='0.0000' sx='1.0' sy='1.0' sz='1.0'></object>
    <object name='TLAMP' x='2.1378' y='3.7000' z='0.0000' rx='0.0000' ry='0.0000' rz='0.0000' sx='1.0' sy='1.0' sz='1.0'></object>
    <object name='TLAMP' x='2.1378' y='2.2000' z='0.0000' rx='0.0000' ry='0.0000' rz='0.0000' sx='1.0' sy='1.0' sz='1.0'></object>
    <object name='TLAMP' x='2.1378' y='0.7000' z='0.0000' rx='0.0000' ry='0.0000' rz='0.0000' sx='1.0' sy='1.0' sz='1.0'></object>
    <object name='TLAMP' x='4.1378' y='3.7000' z='0.0000' rx='0.0000' ry='0.0000' rz='0.0000' sx='1.0' sy='1.0' sz='1.0'></object>
    <object name='TLAMP' x='4.1378' y='2.2000' z='0.0000' rx='0.0000' ry='0.0000' rz='0.0000' sx='1.0' sy='1.0' sz='1.0'></object>
    <object name='TLAMP' x='4.1378' y='0.7000' z='0.0000' rx='0.0000' ry='0.0000' rz='0.0000' sx='1.0' sy='1.0' sz='1.0'></object>
    <object name='TLAMP' x='6.1378' y='3.7000' z='0.0000' rx='0.0000' ry='0.0000' rz='0.0000' sx='1.0' sy='1.0' sz='1.0'></object>
    <object name='TLAMP' x='6.1378' y='2.2000' z='0.0000' rx='0.0000' ry='0.0000' rz='0.0000' sx='1.0' sy='1.0' sz='1.0'></object>
    <object name='TLAMP' x='6.1378' y='0.7000' z='0.0000' rx='0.0000' ry='0.0000' rz='0.0000' sx='1.0' sy='1.0' sz='1.0'></object>
    <object name='TLAMP' x='-6.7000' y='-0.5000' z='0.0000' rx='0.0000' ry='0.0000' rz='0.0000' sx='1.0' sy='1.0' sz='1.0'></object>
    <object name='TLAMP' x='-6.7000' y='-2.0000' z='0.0000' rx='0.0000' ry='0.0000' rz='0.0000' sx='1.0' sy='1.0' sz='1.0'></object>
    <object name='TLAMP' x='-6.7000' y='-3.5000' z='0.0000' rx='0.0000' ry='0.0000' rz='0.0000' sx='1.0' sy='1.0' sz='1.0'></object>
    <object name='TLAMP' x='-4.7000' y='-0.5000' z='0.0000' rx='0.0000' ry='0.0000' rz='0.0000' sx='1.0' sy='1.0' sz='1.0'></object>
    <object name='TLAMP' x='-4.7000' y='-2.0000' z='0.0000' rx='0.0000' ry='0.0000' rz='0.0000' sx='1.0' sy='1.0' sz='1.0'></object>
    <object name='TLAMP' x='-4.7000' y='-3.5000' z='0.0000' rx='0.0000' ry='0.0000' rz='0.0000' sx='1.0' sy='1.0' sz='1.0'></object>
    <object name='TLAMP' x='-2.5000' y='-0.5000' z='0.0000' rx='0.0000' ry='0.0000' rz='0.0000' sx='1.0' sy='1.0' sz='1.0'></object>
    <object name='TLAMP' x='-2.5000' y='-2.0000' z='0.0000' rx='0.0000' ry='0.0000' rz='0.0000' sx='1.0' sy='1.0' sz='1.0'></object>
    <object name='TLAMP' x='-2.5000' y='-3.5000' z='0.0000' rx='0.0000' ry='0.0000' rz='0.0000' sx='1.0' sy='1.0' sz='1.0'></object>
    <object name='TLAMP' x='-0.4000' y='-0.5000' z='0.0000' rx='0.0000' ry='0.0000' rz='0.0000' sx='1.0' sy='1.0' sz='1.0'></object>
    <object name='TLAMP' x='-0.4000' y='-2.0000' z='0.0000' rx='0.0000' ry='0.0000' rz='0.0000' sx='1.0' sy='1.0' sz='1.0'></object>
    <object name='TLAMP' x='-0.4000' y='-3.5000' z='0.0000' rx='0.0000' ry='0.0000' rz='0.0000' sx='1.0' sy='1.0' sz='1.0'></object>
    <object name='TLAMP' x='1.7000' y='-0.5000' z='0.0000' rx='0.0000' ry='0.0000' rz='0.0000' sx='1.0' sy='1.0' sz='1.0'></object>
    <object name='TLAMP' x='1.7000' y='-2.0000' z='0.0000' rx='0.0000' ry='0.0000' rz='0.0000' sx='1.0' sy='1.0' sz='1.0'></object>
    <object name='TLAMP' x='1.7000' y='-3.5000' z='0.0000' rx='0.0000' ry='0.0000' rz='0.0000' sx='1.0' sy='1.0' sz='1.0'></object>
    <object name='TLAMP' x='3.5000' y='-1.0000' z='0.0000' rx='0.0000' ry='0.0000' rz='90.0000' sx='1.0' sy='1.0' sz='1.0'></object>
    <object name='TLAMP' x='5.1000' y='-0.6000' z='0.0000' rx='0.0000' ry='0.0000' rz='0.0000' sx='1.0' sy='1.0' sz='1.0'></object>
    <object name='TLAMP' x='6.4000' y='-1.1000' z='0.0000' rx='0.0000' ry='0.0000' rz='90.0000' sx='1.0' sy='1.0' sz='1.0'></object>
    <object name='TLAMP' x='7.2000' y='-1.1000' z='0.0000' rx='0.0000' ry='0.0000' rz='90.0000' sx='1.0' sy='1.0' sz='1.0'></object>
    <object name='TLAMP' x='5.1000' y='-2.6000' z='0.0000' rx='0.0000' ry='0.0000' rz='0.0000' sx='1.0' sy='1.0' sz='1.0'></object>
    <object name='TLAMP' x='6.4000' y='-3.1000' z='0.0000' rx='0.0000' ry='0.0000' rz='90.0000' sx='1.0' sy='1.0' sz='1.0'></object>
    <object name='TLAMP' x='7.2000' y='-3.1000' z='0.0000' rx='0.0000' ry='0.0000' rz='90.0000' sx='1.0' sy='1.0' sz='1.0'></object>
    <object name='TLAMP' x='5.1000' y='-3.6000' z='0.0000' rx='0.0000' ry='0.0000' rz='0.0000' sx='1.0' sy='1.0' sz='1.0'></object>
    <object name='TLAMP' x='5.1000' y='-1.6000' z='0.0000' rx='0.0000' ry='0.0000' rz='0.0000' sx='1.0' sy='1.0' sz='1.0'></object>
    <object name='MP-2' x='-7.0093' y='3.8118' z='0.0000' rx='0.0000' ry='0.0000' rz='0.0000' sx='1.0' sy='1.0' sz='1.0'></object>
    <object name='MP-2' x='-6.2937' y='3.8118' z='0.0000' rx='0.0000' ry='0.0000' rz='0.0000' sx='1.0' sy='1.0' sz='1.0'></object>
    <object name='MP-2' x='-5.6238' y='3.8118' z='0.0000' rx='0.0000' ry='0.0000' rz='0.0000' sx='1.0' sy='1.0' sz='1.0'></object>
    <object name='MP-2' x='-5.0085' y='3.8118' z='0.0000' rx='0.0000' ry='0.0000' rz='0.0000' sx='1.0' sy='1.0' sz='1.0'></object>
    <object name='S-75' x='-3.7193' y='2.2682' z='2.0000' rx='0.0000' ry='0.0000' rz='-90.0000' sx='1.0' sy='1.0' sz='1.0'></object>
    <object name='MP-2' x='-7.0093' y='-0.1654' z='0.0000' rx='0.0000' ry='0.0000' rz='0.0000' sx='1.0' sy='1.0' sz='1.0'></object>
    <object name='MP-2' x='-6.2937' y='-0.1654' z='0.0000' rx='0.0000' ry='0.0000' rz='0.0000' sx='1.0' sy='1.0' sz='1.0'></object>
    <object name='MP-2' x='-5.6238' y='-0.1654' z='0.0000' rx='0.0000' ry='0.0000' rz='0.0000' sx='1.0' sy='1.0' sz='1.0'></object>
    <object name='MP-2' x='-4.9691' y='-0.1654' z='0.0000' rx='0.0000' ry='0.0000' rz='0.0000' sx='1.0' sy='1.0' sz='1.0'></object>
    <object name='S-75' x='-3.7204' y='-2.1293' z='2.0000' rx='0.0000' ry='0.0000' rz='-90.0000' sx='1.0' sy='1.0' sz='1.0'></object>
    <object name='W-1' x='-1.4844' y='-3.2224' z='0.0000' rx='0.0000' ry='0.0000' rz='-90.0000' sx='1.0' sy='1.0' sz='1.0'></object>
    <object name='S-75' x='0.5286' y='-2.6008' z='2.0000' rx='0.0000' ry='0.0000' rz='-90.0000' sx='1.0' sy='1.0' sz='1.0'></object>
    <object name='K-111' x='3.5926' y='-2.5857' z='0.0000' rx='0.0000' ry='0.0000' rz='0.0000' sx='1.0' sy='1.0' sz='1.0'></object>
    <object name='K-111' x='3.5926' y='-3.7315' z='0.0000' rx='0.0000' ry='0.0000' rz='0.0000' sx='1.0' sy='1.0' sz='1.0'></object>
    <object name='B-67' x='3.4987' y='-0.0284' z='0.0000' rx='0.0000' ry='0.0000' rz='0.0000' sx='1.0' sy='1.0' sz='1.0'></object>
    <object name='LI-4' x='4.1436' y='-1.3095' z='0.0000' rx='0.0000' ry='0.0000' rz='0.0000' sx='1.0' sy='1.0' sz='1.0'></object>
    <object name='S-104' x='3.1331' y='2.5518' z='0.0000' rx='0.0000' ry='0.0000' rz='0.0000' sx='1.0' sy='1.0' sz='1.0'></object>
    <object name='C-1' x='4.3091' y='-0.5561' z='0.0000' rx='0.0000' ry='0.0000' rz='90.0000' sx='1.0' sy='1.0' sz='1.0'></object>
    <object name='C-1' x='4.3091' y='-3.5978' z='0.0000' rx='0.0000' ry='0.0000' rz='90.0000' sx='1.0' sy='1.0' sz='1.0'></object>
    <object name='H-3' x='5.3504' y='-0.0285' z='0.0000' rx='0.0000' ry='0.0000' rz='0.0000' sx='1.0' sy='1.0' sz='1.0'></object>
    <object name='H-3' x='5.3949' y='-4.1309' z='0.0000' rx='0.0000' ry='0.0000' rz='180.0000' sx='1.0' sy='1.0' sz='1.0'></object>
    <object name='H-6' x='4.8049' y='-0.0288' z='0.0000' rx='0.0000' ry='0.0000' rz='0.0000' sx='1.0' sy='1.0' sz='1.0'></object>
    <object name='H-6' x='4.9410' y='-4.1297' z='0.0000' rx='0.0000' ry='0.0000' rz='180.0000' sx='1.0' sy='1.0' sz='1.0'></object>
    <object name='MP-1' x='5.7288' y='-0.1575' z='0.0000' rx='0.0000' ry='0.0000' rz='0.0000' sx='1.0' sy='1.0' sz='1.0'></object>
    <object name='MP-1' x='5.7288' y='-3.9994' z='0.0000' rx='0.0000' ry='0.0000' rz='0.0000' sx='1.0' sy='1.0' sz='1.0'></object>
    <object name='A-3' x='7.1146' y='-4.1307' z='0.0000' rx='0.0000' ry='0.0000' rz='180.0000' sx='1.0' sy='1.0' sz='1.0'></object>
    <object name='H-1' x='7.1153' y='-4.1299' z='0.0000' rx='0.0000' ry='0.0000' rz='180.0000' sx='1.0' sy='1.0' sz='1.0'></object>
    <object name='M-30-60cm' x='5.5457' y='-2.8991' z='0.0000' rx='0.0000' ry='0.0000' rz='0.0000' sx='1.0' sy='1.0' sz='1.0'></object>
    <object name='A-3' x='7.2696' y='-0.0287' z='0.0000' rx='0.0000' ry='0.0000' rz='360.0000' sx='1.0' sy='1.0' sz='1.0'></object>
    <object name='H-1' x='7.2688' y='-0.0294' z='0.0000' rx='0.0000' ry='0.0000' rz='360.0000' sx='1.0' sy='1.0' sz='1.0'></object>
    <object name='C-9' x='6.2332' y='-0.0382' z='0.0000' rx='0.0000' ry='0.0000' rz='0.0000' sx='1.0' sy='1.0' sz='1.0'></object>
    <object name='H-5' x='5.0416' y='-1.1032' z='0.0000' rx='0.0000' ry='0.0000' rz='0.0000' sx='1.0' sy='1.0' sz='1.0'></object>
    <object name='M-30-60cm' x='5.5457' y='-1.2524' z='0.0000' rx='0.0000' ry='0.0000' rz='0.0000' sx='1.0' sy='1.0' sz='1.0'></object>
    <object name='H-5' x='5.0416' y='-3.0574' z='0.0000' rx='0.0000' ry='0.0000' rz='180.0000' sx='1.0' sy='1.0' sz='1.0'></object>
    <object name='H-7' x='5.2071' y='-2.5868' z='0.0000' rx='0.0000' ry='0.0000' rz='90.0000' sx='1.0' sy='1.0' sz='1.0'></object>
    <object name='H-7' x='5.2071' y='-1.5833' z='0.0000' rx='0.0000' ry='0.0000' rz='90.0000' sx='1.0' sy='1.0' sz='1.0'></object>
    <object name='G-1' x='4.7687' y='-1.5472' z='0.0000' rx='0.0000' ry='0.0000' rz='0.0000' sx='1.0' sy='1.0' sz='1.0'></object>
    <object name='G-1' x='4.7687' y='-2.5992' z='0.0000' rx='0.0000' ry='0.0000' rz='0.0000' sx='1.0' sy='1.0' sz='1.0'></object>
    <object name='F-1' x='4.6701' y='-1.1077' z='0.0000' rx='0.0000' ry='0.0000' rz='0.0000' sx='1.0' sy='1.0' sz='1.0'></object>
    <object name='F-1' x='4.6701' y='-3.0604' z='0.0000' rx='0.0000' ry='0.0000' rz='180.0000' sx='1.0' sy='1.0' sz='1.0'></object>
    <object name='MCPTADOBLE' x='-1.4277' y='-4.2047' z='0.0000' rx='0.0000' ry='0.0000' rz='180.0000' sx='1.0' sy='1.0' sz='1.0'></object>
    <object name='MCPTADOBLE' x='0.6810' y='-4.2047' z='0.0000' rx='0.0000' ry='0.0000' rz='0.0000' sx='1.0' sy='1.0' sz='1.0'></object>
    <object name='PTADOBLE' x='0.7310' y='-4.2047' z='0.0000' rx='0.0000' ry='0.0000' rz='0.0000' sx='1.0' sy='1.0' sz='1.0'></object>
    <object name='PTADOBLE' x='2.4310' y='-4.2047' z='0.0000' rx='0.0000' ry='0.0000' rz='180.0000' sx='1.0' sy='1.0' sz='1.0'></object>
    <object name='PTADOBLE' x='-3.1770' y='-4.2079' z='0.0000' rx='0.0000' ry='0.0000' rz='0.0000' sx='1.0' sy='1.0' sz='1.0'></object>
    <object name='PTADOBLE' x='-1.4777' y='-4.2047' z='0.0000' rx='0.0000' ry='0.0000' rz='180.0000' sx='1.0' sy='1.0' sz='1.0'></object>
    <object name='PTASANITARIO2' x='2.7503' y='-1.9613' z='0.0000' rx='0.0000' ry='0.0000' rz='90.0000' sx='1.0' sy='1.0' sz='1.0'></object>
    <object name='MCPTASANITARIO2' x='2.7503' y='-2.0113' z='0.0000' rx='0.0000' ry='0.0000' rz='90.0000' sx='1.0' sy='1.0' sz='1.0'></object>
    <object name='MCPTASANITARIO2' x='7.7915' y='-2.1467' z='0.0000' rx='0.0000' ry='0.0000' rz='-90.0000' sx='1.0' sy='1.0' sz='1.0'></object>
    <object name='PTASANITARIO2' x='7.7915' y='-2.1967' z='0.0000' rx='0.0000' ry='0.0000' rz='-90.0000' sx='1.0' sy='1.0' sz='1.0'></object>
    <object name='MCPTASANITARIO2' x='7.7915' y='-2.0113' z='0.0000' rx='0.0000' ry='0.0000' rz='90.0000' sx='1.0' sy='1.0' sz='1.0'></object>
    <object name='PTASANITARIO2' x='7.7915' y='-1.9613' z='0.0000' rx='0.0000' ry='0.0000' rz='90.0000' sx='1.0' sy='1.0' sz='1.0'></object>
    <object name='PTABANIO' x='5.9094' y='-3.1519' z='0.0000' rx='0.0000' ry='0.0000' rz='90.0000' sx='1.0' sy='1.0' sz='1.0'></object>
    <object name='MCPTABANIO' x='5.9094' y='-4.1295' z='0.0000' rx='0.0000' ry='0.0000' rz='90.0000' sx='1.0' sy='1.0' sz='1.0'></object>
    <object name='PTABANIO' x='5.9094' y='-1.0068' z='0.0000' rx='0.0000' ry='0.0000' rz='-90.0000' sx='1.0' sy='-1.0' sz='1.0'></object>
    <object name='MCPTABANIO' x='5.9094' y='-0.0296' z='0.0000' rx='0.0000' ry='0.0000' rz='-90.0000' sx='1.0' sy='-1.0' sz='1.0'></object>
</scene>
